{
    "key": "group_5d6e6090ab492",
    "title": "Block - Flex",
    "fields": [
        {
            "key": "field_5e41191652109",
            "label": "Content",
            "name": "",
            "type": "tab",
            "instructions": "",
            "required": 0,
            "conditional_logic": 0,
            "wrapper": {
                "width": "",
                "class": "",
                "id": ""
            },
            "placement": "top",
            "endpoint": 0
        },
        {
            "key": "field_5d6e60ac61b0e",
            "label": "Title",
            "name": "block_flex_title",
            "type": "text",
            "instructions": "",
            "required": 0,
            "conditional_logic": 0,
            "wrapper": {
                "width": "",
                "class": "",
                "id": ""
            },
            "default_value": "",
            "placeholder": "",
            "prepend": "",
            "append": "",
            "maxlength": "",
            "translations": "translate"
        },
        {
            "key": "field_5d6e60d7173e5",
            "label": "Items",
            "name": "block_flex_repeater",
            "type": "repeater",
            "instructions": "",
            "required": 0,
            "conditional_logic": 0,
            "wrapper": {
                "width": "",
                "class": "",
                "id": ""
            },
            "collapsed": "",
            "min": 2,
            "max": 0,
            "layout": "row",
            "button_label": "Add column",
            "sub_fields": [
                {
                    "key": "field_623462af5795a",
                    "label": "Image",
                    "name": "image",
                    "type": "image",
                    "instructions": "",
                    "required": 0,
                    "conditional_logic": 0,
                    "wrapper": {
                        "width": "",
                        "class": "",
                        "id": ""
                    },
                    "return_format": "array",
                    "preview_size": "thumbnail",
                    "library": "all",
                    "min_width": "",
                    "min_height": "",
                    "min_size": "",
                    "max_width": "",
                    "max_height": "",
                    "max_size": "",
                    "mime_types": "",
                    "translations": "copy_once"
                },
                {
                    "key": "field_623462bf5795b",
                    "label": "Title",
                    "name": "title",
                    "type": "text",
                    "instructions": "",
                    "required": 0,
                    "conditional_logic": 0,
                    "wrapper": {
                        "width": "",
                        "class": "",
                        "id": ""
                    },
                    "default_value": "",
                    "placeholder": "",
                    "prepend": "",
                    "append": "",
                    "maxlength": "",
                    "translations": "translate"
                },
                {
                    "key": "field_623462c45795c",
                    "label": "Text",
                    "name": "text",
                    "type": "wysiwyg",
                    "instructions": "",
                    "required": 0,
                    "conditional_logic": 0,
                    "wrapper": {
                        "width": "",
                        "class": "",
                        "id": ""
                    },
                    "default_value": "",
                    "tabs": "all",
                    "toolbar": "basic",
                    "media_upload": 0,
                    "delay": 0,
                    "translations": "translate"
                },
                {
                    "key": "field_623462e25795d",
                    "label": "Link",
                    "name": "link",
                    "type": "link",
                    "instructions": "",
                    "required": 0,
                    "conditional_logic": 0,
                    "wrapper": {
                        "width": "",
                        "class": "",
                        "id": ""
                    },
                    "return_format": "array",
                    "translations": "copy_once"
                },
                {
                    "key": "field_623462f15795e",
                    "label": "Button Type",
                    "name": "button_type",
                    "type": "select",
                    "instructions": "",
                    "required": 0,
                    "conditional_logic": [
                        [
                            {
                                "field": "field_623462e25795d",
                                "operator": "!=empty"
                            }
                        ]
                    ],
                    "wrapper": {
                        "width": "",
                        "class": "",
                        "id": ""
                    },
                    "choices": {
                        "primary": "Primary",
                        "secondary": "Secondary",
                        "link": "Link"
                    },
                    "default_value": "primary",
                    "allow_null": 0,
                    "multiple": 0,
                    "ui": true,
                    "return_format": "value",
                    "translations": "copy_once",
                    "ajax": 0,
                    "placeholder": ""
                }
            ]
        },
        {
            "key": "field_5e4122f6e77d7",
            "label": "Options",
            "name": "",
            "type": "tab",
            "instructions": "",
            "required": 0,
            "conditional_logic": 0,
            "wrapper": {
                "width": "",
                "class": "",
                "id": ""
            },
            "placement": "top",
            "endpoint": 0
        },
        {
            "key": "field_5e412433e77d8",
            "label": "Spacing top",
            "name": "block_flex_spacing_top",
            "type": "true_false",
            "instructions": "",
            "required": 0,
            "conditional_logic": 0,
            "wrapper": {
                "width": "",
                "class": "",
                "id": ""
            },
            "message": "",
            "default_value": 1,
            "ui": true,
            "ui_on_text": "",
            "ui_off_text": "",
            "translations": "copy_once"
        },
        {
            "key": "field_5e41243ee77d9",
            "label": "Spacing bottom",
            "name": "block_flex_spacing_bottom",
            "type": "true_false",
            "instructions": "",
            "required": 0,
            "conditional_logic": 0,
            "wrapper": {
                "width": "",
                "class": "",
                "id": ""
            },
            "message": "",
            "default_value": 1,
            "ui": true,
            "ui_on_text": "",
            "ui_off_text": "",
            "translations": "copy_once"
        },
        {
            "key": "field_5da42b19a4c03",
            "label": "Number of columns",
            "name": "block_flex_column_number",
            "type": "select",
            "instructions": "",
            "required": 0,
            "conditional_logic": 0,
            "wrapper": {
                "width": "",
                "class": "",
                "id": ""
            },
            "choices": {
                "2": "2",
                "3": "3",
                "4": "4"
            },
            "default_value": 2,
            "allow_null": 0,
            "multiple": 0,
            "ui": true,
            "ajax": 0,
            "return_format": "value",
            "translations": "copy_once",
            "placeholder": ""
        }
    ],
    "location": [
        [
            {
                "param": "block",
                "operator": "==",
                "value": "acf\/block-flex"
            }
        ]
    ],
    "menu_order": 0,
    "position": "normal",
    "style": "default",
    "label_placement": "top",
    "instruction_placement": "label",
    "hide_on_screen": "",
    "active": true,
    "description": "",
    "show_in_rest": 0,
    "modified": 1647600455
}